trolled/__init__.py
trolled/main.py
trolled-0.0.1.dist-info/METADATA
trolled-0.0.1.dist-info/WHEEL
trolled-0.0.1.dist-info/license
trolled-0.0.1.dist-info/top_level.txt
trolled-0.0.1.dist-info/RECORD
