Metadata-Version: 2.1
Name: trolled
Version: 0.0.1
Summary: :DD
Home-page: https://github.com/co-existing/trolled
Author: co-existing
Author-email: aarontian2019@gmail.com
Project-URL: Bug Tracker, https://github.com/co-existing/trolled/issues
Classifier: Programming Language :: Python :: 3
Classifier: License :: OSI Approved :: MIT License
Classifier: Operating System :: OS Independent
Requires-Python: >=3.6
License-File: license
